kfs.py
kungfu.dll
kungfubuildinfo.json
libnode.dll
libnodebuildinfo.json
pykungfu.cp39-win_amd64.pyd
kungfu/__init__.py
kungfu/__main__.py
kungfu/__tool__.py
kungfu/console/__init__.py
kungfu/console/site.py
kungfu/console/bridging/__init__.py
kungfu/console/bridging/__registry__.py
kungfu/console/bridging/black/__init__.py
kungfu/console/bridging/black/__main__.py
kungfu/console/bridging/nuitka/__init__.py
kungfu/console/bridging/nuitka/__main__.py
kungfu/console/bridging/pdm/__init__.py
kungfu/console/bridging/pdm/__main__.py
kungfu/console/bridging/scons/__init__.py
kungfu/console/bridging/scons/__main__.py
kungfu/console/commands/__init__.py
kungfu/console/commands/__registry__.py
kungfu/console/commands/assemble.py
kungfu/console/commands/cli.py
kungfu/console/commands/engage.py
kungfu/console/commands/journal.py
kungfu/console/commands/run.py
kungfu/console/variants/__init__.py
kungfu/console/variants/__registry__.py
kungfu/console/variants/node.py
kungfu/console/variants/python.py
kungfu/wingchun/__init__.py
kungfu/wingchun/calendar.py
kungfu/wingchun/constants.py
kungfu/wingchun/msg.py
kungfu/wingchun/replay.py
kungfu/wingchun/strategy.py
kungfu/wingchun/utils.py
kungfu/yijinjing/__init__.py
kungfu/yijinjing/journal.py
kungfu/yijinjing/locator.py
kungfu/yijinjing/log.py
kungfu/yijinjing/time.py
kungfu/yijinjing/utils.py
kungfu/yijinjing/data/__init__.py
kungfu/yijinjing/data/adapter.py
kungfu/yijinjing/practice/__init__.py
kungfu/yijinjing/practice/apprentice.py
kungfu/yijinjing/practice/coloop.py
kungfu/yijinjing/practice/executor.py
kungfu/yijinjing/practice/master.py
kungfu/yijinjing/sinks/__init__.py
kungfu/yijinjing/sinks/archive.py
kungfu/yijinjing/sinks/csv.py
kungfu_core.egg-info/PKG-INFO
kungfu_core.egg-info/SOURCES.txt
kungfu_core.egg-info/dependency_links.txt
kungfu_core.egg-info/entry_points.txt
kungfu_core.egg-info/requires.txt
kungfu_core.egg-info/top_level.txt
pyi-hooks/__init__.py
pyi-hooks/hook-blib2to3.py
pyi-hooks/hook-nuitka.py
pyi-hooks/hook-pdm.py
pyi-hooks/hook-pep517.py
pyi-hooks/hook-pip.py
pyi-hooks/pre_find_module_path/__init__.py
pyi-hooks/pre_find_module_path/hook-nuitka.py
pyi-hooks/pre_safe_import_module/__init__.py
kungfu_core-2.4.77a1.dist-info/METADATA
kungfu_core-2.4.77a1.dist-info/WHEEL
kungfu_core-2.4.77a1.dist-info/entry_points.txt
kungfu_core-2.4.77a1.dist-info/top_level.txt
kungfu_core-2.4.77a1.dist-info/RECORD
