Metadata-Version: 2.1
Name: kungfu-core
Version: 2.4.77a1
Home-page: https://www.kungfu-trader.com
Author: Kungfu Trader <info@kungfu.link>
License: Apache-2.0
Project-URL: repository, https://github.com/kungfu-trader/kungfu.git
Requires-Dist: click (==8.1.3)
Requires-Dist: psutil (<5.10.0,>=5.9.0)
Requires-Dist: tabulate (<0.9.0,>=0.8.10)
Requires-Dist: wcmatch (<8.1.0,>=8.0.0)
Requires-Dist: numpy (<1.25.0,>=1.24.0)
Requires-Dist: pandas (<2.1.0,>=2.0.0)
Requires-Dist: scipy (<1.9.0,>=1.8.0)
Requires-Dist: statsmodels (<0.14.0,>=0.13.5)
Requires-Dist: openpyxl (<3.2.0,>=3.1.2)
Requires-Dist: ordered-set (<4.2.0,>=4.1.0)
